stat_code_pyt/__init__.py
stat_code_pyt/main.py
Stat_code_pyt-0.0.1.dist-info/METADATA
Stat_code_pyt-0.0.1.dist-info/WHEEL
Stat_code_pyt-0.0.1.dist-info/top_level.txt
Stat_code_pyt-0.0.1.dist-info/RECORD
